directory_watcher/__init__.py
directory_watcher/directory_watcher.py
directory_watcher_bbushvt-1.0.0.dist-info/LICENSE
directory_watcher_bbushvt-1.0.0.dist-info/METADATA
directory_watcher_bbushvt-1.0.0.dist-info/WHEEL
directory_watcher_bbushvt-1.0.0.dist-info/top_level.txt
directory_watcher_bbushvt-1.0.0.dist-info/RECORD
